robothub_sdk/__init__.py
robothub_sdk-0.0.3.dist-info/METADATA
robothub_sdk-0.0.3.dist-info/WHEEL
robothub_sdk-0.0.3.dist-info/top_level.txt
robothub_sdk-0.0.3.dist-info/RECORD
