Metadata-Version: 2.1
Name: robothub-sdk
Version: 0.0.3
Summary: RobotHub SDK is a Python package allowing to communicate with RobotHub platform
Home-page: https://www.luxonis.com/
Author: Luxonis
Author-email: support@luxonis.com
License: UNKNOWN
Project-URL: Documentation, https://docs.luxonis.com/projects/robothub/en/latest/
Keywords: robothub sdk depthai robot hub connect agent
Platform: UNKNOWN
Classifier: Programming Language :: Python
Classifier: Programming Language :: Python :: 3
Classifier: Programming Language :: Python :: 3.6
Classifier: Programming Language :: Python :: 3.7
Classifier: Programming Language :: Python :: 3.8
Classifier: Programming Language :: Python :: 3.9
Requires-Dist: depthai-sdk
Requires-Dist: depthai
Requires-Dist: opencv-python
Requires-Dist: paho-mqtt
Requires-Dist: paho-socket
